LSHlink/__init__.py
LSHlink_ffghcv-0.2.dist-info/LICENSE
LSHlink_ffghcv-0.2.dist-info/METADATA
LSHlink_ffghcv-0.2.dist-info/WHEEL
LSHlink_ffghcv-0.2.dist-info/top_level.txt
LSHlink_ffghcv-0.2.dist-info/RECORD
